adef_tools/__init__.py
adef_tools/adef_fn.py
adef_tools/adef_intg_fn.py
adef_tools/cli.py
adef_tools/interactive.py
adef_tools/main_legacy.py
adef_tools/raster.py
adef_tools/utils.py
adef_tools/utils_adef.py
adef_tools/vector.py
adef_tools-0.6.2.dist-info/METADATA
adef_tools-0.6.2.dist-info/WHEEL
adef_tools-0.6.2.dist-info/entry_points.txt
adef_tools-0.6.2.dist-info/licenses/LICENSE
adef_tools-0.6.2.dist-info/RECORD
