Metadata-Version: 2.4
Name: adef-tools
Version: 0.6.2
Summary: Script to work with Integrated Alert Deforestacion
Project-URL: repository, https://git.icf.gob.hn/alopez/adef-integ-tools
Project-URL: homepage, https://git.icf.gob.hn/alopez/adef-integ-tools
Project-URL: issues, https://git.icf.gob.hn/alopez/adef-integ-tools/-/issues
Author-email: Luis Alfredo López Gonzales <lalgonzales@gmail.com>
License: MIT
License-File: LICENSE
Keywords: alert,analysis,deforestation,geospatial,integrated,monitoring
Classifier: Intended Audience :: Developers
Classifier: License :: OSI Approved :: MIT License
Classifier: Operating System :: OS Independent
Classifier: Programming Language :: Python :: 3.10
Classifier: Programming Language :: Python :: 3.11
Classifier: Programming Language :: Python :: 3.12
Classifier: Topic :: Software Development :: Libraries :: Python Modules
Requires-Python: >=3.10
Requires-Dist: dask[distributed]>=2025.4.1
Requires-Dist: gdal>=3.11.0.1
Requires-Dist: geoalchemy2>=0.17.1
Requires-Dist: geopandas>=1.0.1
Requires-Dist: matplotlib>=3.10.1
Requires-Dist: owslib>=0.33.0
Requires-Dist: psycopg2>=2.9.10
Requires-Dist: pyarrow>=20.0.0
Requires-Dist: python-dotenv>=1.1.0
Requires-Dist: rioxarray>=0.19.0
Requires-Dist: sqlalchemy>=2.0.41
Requires-Dist: tqdm>=4.67.1
Provides-Extra: dask
Requires-Dist: dask-geopandas>=0.5.0; extra == 'dask'
